setup.py
django_timeline.egg-info/PKG-INFO
django_timeline.egg-info/SOURCES.txt
django_timeline.egg-info/dependency_links.txt
django_timeline.egg-info/requires.txt
django_timeline.egg-info/top_level.txt
timeline/__init__.py
timeline/base.py
timeline/models.py
timeline/tests.py
timeline/templatetags/__init__.py
timeline/templatetags/event_tags.py