Metadata-Version: 1.1
Name: django-timeline
Version: 0.5
Summary: a Django timeline (activity stream) using redis
Home-page: https://github.com/tiltshift/django-timeline.git
Author: Chris Drackett
Author-email: chris@tiltshiftstudio.com
License: UNKNOWN
Platform: UNKNOWN
Classifier: Development Status :: 4 - Beta
Classifier: Environment :: Web Environment
Classifier: Intended Audience :: Developers
Classifier: License :: OSI Approved :: BSD License
Classifier: Operating System :: OS Independent
Classifier: Programming Language :: Python
Classifier: Framework :: Django
